{
  "id": 72,
  "age_ratings": [
    11721,
    32022,
    47684,
    47685,
    47687,
    125644,
    140774
  ],
  "aggregated_rating": 92.44444444444444,
  "aggregated_rating_count": 12,
  "alternative_names": [
    50135
  ],
  "artworks": [
    36972
  ],
  "bundles": [
    55025,
    191406
  ],
  "category": 0,
  "collection": 87,
  "cover": {
    "id": 82660,
    "alpha_channel": false,
    "animated": false,
    "game": 72,
    "height": 1948,
    "image_id": "co1rs4",
    "url": "//images.igdb.com/igdb/image/upload/t_thumb/co1rs4.jpg",
    "width": 1461,
    "checksum": "01d5fb19-7bb3-ad32-8f7b-351a05a2fb57"
  },
  "created_at": 1297956069,
  "dlcs": [
    99969,
    114140
  ],
  "external_games": [
    {
      "id": 15150,
      "category": 1,
      "created_at": 1494750736,
      "game": 72,
      "name": "Portal 2",
      "uid": "620",
      "updated_at": 1633093180,
      "checksum": "0aa230d0-8071-b14d-2b57-1611a4c5c63a"
    },
    {
      "id": 137388,
      "category": 3,
      "created_at": 1502465726,
      "game": 72,
      "name": "Portal 2",
      "uid": "21662",
      "updated_at": 1709121884,
      "url": "https://www.giantbomb.com/games/3030-21662/",
      "year": 2011,
      "checksum": "83b05018-e054-9eda-dd5c-a72a98c2e3f1"
    },
    {
      "id": 189642,
      "category": 10,
      "created_at": 1483134014,
      "game": 72,
      "name": "Portal 2",
      "uid": "UCnj3zKNoYGZLWzFAo-bB3BQ",
      "updated_at": 1709121883,
      "url": "https://gaming.youtube.com/game/UCnj3zKNoYGZLWzFAo-bB3BQ",
      "checksum": "c24f7a9f-af20-cb64-a891-45d62b789a9d"
    },
    {
      "id": 214010,
      "category": 11,
      "created_at": 1516797419,
      "game": 72,
      "name": "Portal 2",
      "uid": "xbox36066acd000-77fe-1000-9115-d80245410912",
      "updated_at": 1709121884,
      "url": "http://marketplace.xbox.com/en-US/Product/Portal-2/66acd000-77fe-1000-9115-d80245410912",
      "year": 2011,
      "checksum": "3efb317e-5279-7d8e-102b-2a396e13e0fd"
    },
    {
      "id": 245334,
      "category": 14,
      "created_at": 1519314880,
      "game": 72,
      "name": "Portal 2",
      "uid": "19731",
      "updated_at": 1709121883,
      "url": "https://www.twitch.tv/directory/game/Portal 2",
      "checksum": "22ba7a49-9df1-1f41-275e-01252e1a3007"
    },
    {
      "id": 1929756,
      "category": 20,
      "created_at": 1598354780,
      "game": 72,
      "uid": "B004IEA4QE",
      "updated_at": 1709121884,
      "url": "https://amazon.com/dp/B004IEA4QE",
      "checksum": "c3b0b3e7-43be-32c4-272c-b5a1ec0035ef"
    },
    {
      "id": 1931953,
      "category": 20,
      "created_at": 1598356387,
      "game": 72,
      "uid": "B003O6E3C8",
      "updated_at": 1709121884,
      "checksum": "463ea33f-b1a2-beaf-0d4c-a24450240064"
    },
    {
      "id": 2082680,
      "category": 11,
      "created_at": 1628776162,
      "game": 72,
      "name": "Portal 2",
      "uid": "BT2B17V20D1P",
      "updated_at": 1628798205,
      "url": "https://www.microsoft.com/en-us/p/-1-/BT2B17V20D1P",
      "year": 2011,
      "checksum": "6350806f-d128-15a2-1f03-f918baa07e69"
    },
    {
      "id": 2161690,
      "category": 31,
      "created_at": 1635272369,
      "game": 72,
      "name": "Portal 2",
      "uid": "66acd000-77fe-1000-9115-d80245410912",
      "updated_at": 1635851335,
      "url": "https://marketplace.xbox.com//en-US/Product/Portal-2/66acd000-77fe-1000-9115-d80245410912",
      "checksum": "f4ba692c-389c-6505-7f03-fafe5eb28a12"
    }
  ],
  "first_release_date": 1303084800,
  "franchises": [
    1724
  ],
  "game_engines": [
    3
  ],
  "game_modes": [
    1,
    2,
    3,
    4
  ],
  "genres": [
    {
      "id": 5,
      "created_at": 1297639288,
      "name": "Shooter",
      "slug": "shooter",
      "updated_at": 1323289215,
      "url": "https://www.igdb.com/genres/shooter",
      "checksum": "ee167402-1696-17fa-b3c6-692c94837018"
    },
    {
      "id": 8,
      "created_at": 1297639288,
      "name": "Platform",
      "slug": "platform",
      "updated_at": 1323289215,
      "url": "https://www.igdb.com/genres/platform",
      "checksum": "7e69f327-90df-3ca6-0cdf-c8c34b633522"
    },
    {
      "id": 9,
      "created_at": 1297639288,
      "name": "Puzzle",
      "slug": "puzzle",
      "updated_at": 1323289215,
      "url": "https://www.igdb.com/genres/puzzle",
      "checksum": "0a3c4bb4-2c52-bc4a-1502-2f6086a62169"
    },
    {
      "id": 31,
      "created_at": 1323568041,
      "name": "Adventure",
      "slug": "adventure",
      "updated_at": 1323568041,
      "url": "https://www.igdb.com/genres/adventure",
      "checksum": "84da7880-b95f-f981-9c8d-b291bebff079"
    }
  ],
  "involved_companies": [
    {
      "id": 265481,
      "company": 56,
      "created_at": 1714974459,
      "developer": true,
      "game": 72,
      "porting": false,
      "publisher": true,
      "supporting": false,
      "updated_at": 1715195616,
      "checksum": "f6b51e6e-af76-4894-6a53-e875942555ff"
    },
    {
      "id": 265482,
      "company": 1,
      "created_at": 1714974459,
      "developer": false,
      "game": 72,
      "porting": false,
      "publisher": true,
      "supporting": false,
      "updated_at": 1715262687,
      "checksum": "bf8e0bb2-7954-1d9c-0f4d-27607573d505"
    },
    {
      "id": 265779,
      "company": 56,
      "created_at": 1715195607,
      "developer": true,
      "game": 72,
      "porting": false,
      "publisher": false,
      "supporting": false,
      "updated_at": 1716354282,
      "checksum": "1bc89e23-db6f-34ff-1d02-b6c49f243f56"
    },
    {
      "id": 265780,
      "company": 56,
      "created_at": 1715195608,
      "developer": false,
      "game": 72,
      "porting": false,
      "publisher": true,
      "supporting": false,
      "updated_at": 1716354282,
      "checksum": "0230ebd5-3fe1-006d-fc1b-adf92f2a911b"
    }
  ],
  "keywords": [
    {
      "id": 453,
      "created_at": 1381649008,
      "name": "first person shooter",
      "slug": "first-person-shooter",
      "updated_at": 1381649008,
      "url": "https://www.igdb.com/categories/first-person-shooter",
      "checksum": "5bcd878a-39be-d39b-a2a8-33f8010c247f"
    },
    {
      "id": 575,
      "created_at": 1385900074,
      "name": "robots",
      "slug": "robots",
      "updated_at": 1385900074,
      "url": "https://www.igdb.com/categories/robots",
      "checksum": "399f7079-6419-7a09-4022-044a45451b7d"
    },
    {
      "id": 592,
      "created_at": 1387409050,
      "name": "elves",
      "slug": "elves",
      "updated_at": 1387409050,
      "url": "https://www.igdb.com/categories/elves",
      "checksum": "76a11e4a-cf1b-c15e-ce7f-289623890407"
    },
    {
      "id": 962,
      "created_at": 1397946811,
      "name": "female protagonist",
      "slug": "female-protagonist",
      "updated_at": 1397946811,
      "url": "https://www.igdb.com/categories/female-protagonist",
      "checksum": "525883fd-9ddf-a887-6f67-54e25f8a4204"
    },
    {
      "id": 1158,
      "created_at": 1407837958,
      "name": "steam",
      "slug": "steam",
      "updated_at": 1407837958,
      "url": "https://www.igdb.com/categories/steam",
      "checksum": "e6296b7c-79f3-8a67-cda7-55bed1e9868d"
    },
    {
      "id": 1181,
      "created_at": 1408293960,
      "name": "fairy",
      "slug": "fairy",
      "updated_at": 1408293960,
      "url": "https://www.igdb.com/categories/fairy",
      "checksum": "b51b19b6-3a4a-bcc0-a4b5-904e8e087487"
    },
    {
      "id": 1293,
      "created_at": 1414966316,
      "name": "achievements",
      "slug": "achievements",
      "updated_at": 1414966316,
      "url": "https://www.igdb.com/categories/achievements",
      "checksum": "8f60eef3-a51d-d733-700a-2da3e95d69b4"
    },
    {
      "id": 1440,
      "created_at": 1428763439,
      "name": "artificial intelligence",
      "slug": "artificial-intelligence",
      "updated_at": 1428763439,
      "url": "https://www.igdb.com/categories/artificial-intelligence",
      "checksum": "ad291226-d874-a234-5ebb-65831573fb56"
    },
    {
      "id": 2071,
      "created_at": 1451428926,
      "name": "sequel",
      "slug": "sequel",
      "updated_at": 1451428926,
      "url": "https://www.igdb.com/categories/sequel",
      "checksum": "9fd9696d-1526-fbdb-76bc-bbcdcdb7ee02"
    },
    {
      "id": 4004,
      "created_at": 1503322887,
      "name": "steam achievements",
      "slug": "steam-achievements",
      "updated_at": 1503322887,
      "url": "https://www.igdb.com/categories/steam-achievements",
      "checksum": "3b82425f-b8f2-dd06-3a80-a137a6088f94"
    },
    {
      "id": 4134,
      "created_at": 1507131366,
      "name": "digital distribution",
      "slug": "digital-distribution",
      "updated_at": 1507131366,
      "url": "https://www.igdb.com/categories/digital-distribution",
      "checksum": "4a58991d-93e1-39bd-2a8b-2f102143d0cc"
    },
    {
      "id": 4162,
      "created_at": 1507132046,
      "name": "anthropomorphism",
      "slug": "anthropomorphism",
      "updated_at": 1507132046,
      "url": "https://www.igdb.com/categories/anthropomorphism",
      "checksum": "e594ab11-9553-451a-88d3-fc954a602597"
    },
    {
      "id": 4266,
      "created_at": 1507133139,
      "name": "alternate costumes",
      "slug": "alternate-costumes",
      "updated_at": 1507133139,
      "url": "https://www.igdb.com/categories/alternate-costumes",
      "checksum": "12e21a66-0592-7d21-a32c-5c60bc9247d7"
    },
    {
      "id": 4345,
      "created_at": 1507133765,
      "name": "bink video",
      "slug": "bink-video",
      "updated_at": 1507133765,
      "url": "https://www.igdb.com/categories/bink-video",
      "checksum": "76201387-ac62-d78a-0887-40335ac1109e"
    },
    {
      "id": 4578,
      "created_at": 1507150473,
      "name": "motion blur",
      "slug": "motion-blur",
      "updated_at": 1507150473,
      "url": "https://www.igdb.com/categories/motion-blur",
      "checksum": "17ce05e0-d1dc-201e-7c78-ed41548020f7"
    },
    {
      "id": 4725,
      "created_at": 1507155279,
      "name": "young protagonist",
      "slug": "young-protagonist",
      "updated_at": 1507155279,
      "url": "https://www.igdb.com/categories/young-protagonist",
      "checksum": "a09fbeb1-de71-fd7e-884f-04aec423771d"
    },
    {
      "id": 4956,
      "created_at": 1507207096,
      "name": "a.i. companion",
      "slug": "ai-companion",
      "updated_at": 1507207096,
      "url": "https://www.igdb.com/categories/ai-companion",
      "checksum": "1f806c7f-0b87-f587-b186-27f8d1338b43"
    },
    {
      "id": 4974,
      "created_at": 1507208075,
      "name": "male antagonist",
      "slug": "male-antagonist",
      "updated_at": 1507208075,
      "url": "https://www.igdb.com/categories/male-antagonist",
      "checksum": "e6d8788f-103a-4528-24a5-c46e13bb448b"
    },
    {
      "id": 5633,
      "created_at": 1507280687,
      "name": "xbox one backwards compatibility",
      "slug": "xbox-one-backwards-compatibility",
      "updated_at": 1507280687,
      "url": "https://www.igdb.com/categories/xbox-one-backwards-compatibility",
      "checksum": "9c468ca5-2b68-bfb5-1760-f584efc77d66"
    },
    {
      "id": 5938,
      "created_at": 1507282896,
      "name": "dimension travel",
      "slug": "dimension-travel",
      "updated_at": 1507282896,
      "url": "https://www.igdb.com/categories/dimension-travel",
      "checksum": "10fcb7de-b000-9de0-9e8b-362a7b820945"
    },
    {
      "id": 6137,
      "created_at": 1507285728,
      "name": "linear gameplay",
      "slug": "linear-gameplay",
      "updated_at": 1507285728,
      "url": "https://www.igdb.com/categories/linear-gameplay",
      "checksum": "7b6982dd-b902-ecdc-7b5f-55bbac83dab7"
    },
    {
      "id": 6326,
      "created_at": 1507285964,
      "name": "ambient music",
      "slug": "ambient-music",
      "updated_at": 1507285964,
      "url": "https://www.igdb.com/categories/ambient-music",
      "checksum": "86fdfec0-402e-59ef-933c-5a5c884f7993"
    },
    {
      "id": 6735,
      "created_at": 1507287901,
      "name": "first-person platforming",
      "slug": "first-person-platforming",
      "updated_at": 1507287901,
      "url": "https://www.igdb.com/categories/first-person-platforming",
      "checksum": "90baff7b-60e3-8be8-8caf-a99f9fe598da"
    },
    {
      "id": 7313,
      "created_at": 1507292344,
      "name": "monster capturing",
      "slug": "monster-capturing",
      "updated_at": 1507292344,
      "url": "https://www.igdb.com/categories/monster-capturing",
      "checksum": "87f634df-1f9f-a47a-aba6-93ca67a4348e"
    },
    {
      "id": 7570,
      "created_at": 1507296695,
      "name": "developer commentary",
      "slug": "developer-commentary",
      "updated_at": 1507296695,
      "url": "https://www.igdb.com/categories/developer-commentary",
      "checksum": "47f716ad-9da8-eeee-b962-315261dc2fc3"
    },
    {
      "id": 8262,
      "created_at": 1507491024,
      "name": "a.i. construct",
      "slug": "ai-construct",
      "updated_at": 1507491024,
      "url": "https://www.igdb.com/categories/ai-construct",
      "checksum": "b56d7398-7bfd-d862-a30a-d66586acdc41"
    },
    {
      "id": 8896,
      "created_at": 1507543792,
      "name": "another world",
      "slug": "another-world",
      "updated_at": 1507543792,
      "url": "https://www.igdb.com/categories/another-world",
      "checksum": "602a33a5-1a84-bb48-a266-b5e073447b09"
    },
    {
      "id": 10435,
      "created_at": 1507819845,
      "name": "renderware",
      "slug": "renderware",
      "updated_at": 1507819845,
      "url": "https://www.igdb.com/categories/renderware",
      "checksum": "04a6e5b4-f28b-f347-cf48-6b6d1a6cf96b"
    },
    {
      "id": 11208,
      "created_at": 1512708598,
      "name": "avatar awards",
      "slug": "avatar-awards",
      "updated_at": 1512708598,
      "url": "https://www.igdb.com/categories/avatar-awards",
      "checksum": "025d914f-2acc-abb8-8fb4-2c9e177d021f"
    }
  ],
  "multiplayer_modes": [
    11591,
    11592,
    11593,
    11594,
    11595
  ],
  "name": "Portal 2",
  "platforms": [
    3,
    6,
    9,
    12,
    14,
    130
  ],
  "player_perspectives": [
    1
  ],
  "rating": 91.72150028093169,
  "rating_count": 3434,
  "release_dates": [
    461497,
    461498,
    485080,
    591612,
    591613,
    591614,
    591615,
    591616,
    591617,
    591618
  ],
  "screenshots": [
    {
      "id": 725,
      "game": 72,
      "height": 1080,
      "image_id": "i9ys3zdhph1mh3futdit",
      "url": "//images.igdb.com/igdb/image/upload/t_thumb/i9ys3zdhph1mh3futdit.jpg",
      "width": 1920,
      "checksum": "f26d594c-6308-4cdb-bd15-024ed4889b63"
    },
    {
      "id": 726,
      "game": 72,
      "height": 1080,
      "image_id": "rvrge8js7xnhr4z1vrbk",
      "url": "//images.igdb.com/igdb/image/upload/t_thumb/rvrge8js7xnhr4z1vrbk.jpg",
      "width": 1920,
      "checksum": "8375399a-2226-e657-ec60-3f6569c33c88"
    },
    {
      "id": 727,
      "game": 72,
      "height": 1080,
      "image_id": "cmxaa4r52exlqvzwtxkh",
      "url": "//images.igdb.com/igdb/image/upload/t_thumb/cmxaa4r52exlqvzwtxkh.jpg",
      "width": 1920,
      "checksum": "aaa17d56-ea48-7092-504c-5d2da782edb5"
    },
    {
      "id": 728,
      "game": 72,
      "height": 1080,
      "image_id": "vghkwbdabx0cri7thb9y",
      "url": "//images.igdb.com/igdb/image/upload/t_thumb/vghkwbdabx0cri7thb9y.jpg",
      "width": 1920,
      "checksum": "13e9a6dc-1d8e-1fc8-7897-1db75dc8c743"
    },
    {
      "id": 729,
      "game": 72,
      "height": 1080,
      "image_id": "m4hdhjptmmwvrjbojzp0",
      "url": "//images.igdb.com/igdb/image/upload/t_thumb/m4hdhjptmmwvrjbojzp0.jpg",
      "width": 1920,
      "checksum": "3f7ecd7b-014c-4edd-57af-03459a14e229"
    }
  ],
  "similar_games": [
    471,
    1341,
    7350,
    11646,
    16992,
    17447,
    28070,
    55173,
    55190,
    56033
  ],
  "slug": "portal-2",
  "storyline": "You lost your memory, you are alone in a world full of danger, and your mission is survive using your mind. The only way to get out from this hell is.....Hi i'm GLAdOS, and welcome to the amazing world of portal 2, here i will expose you to a lot of tests, and try to k.. help Aperture Science envolve in a new era.\nYour job is advance in the levels i propose and get better and better, you will have an portal gun to help you, and remember nothing is impossible if you try, and try again and again and again....\nThe puzzles are waiting for you!",
  "summary": "Sequel to the acclaimed Portal (2007), Portal 2 pits the protagonist of the original game, Chell, and her new robot friend, Wheatley, against more puzzles conceived by GLaDOS, an A.I. with the sole purpose of testing the Portal Gun's mechanics and taking revenge on Chell for the events of Portal. As a result of several interactions and revelations, Chell once again pushes to escape Aperture Science Labs.",
  "tags": [
    1,
    18,
    27,
    268435461,
    268435464,
    268435465,
    268435487,
    536871365,
    536871487,
    536871504,
    536871874,
    536872070,
    536872093,
    536872205,
    536872352,
    536872983,
    536874916,
    536875046,
    536875074,
    536875178,
    536875257,
    536875490,
    536875637,
    536875868,
    536875886,
    536876545,
    536876850,
    536877049,
    536877238,
    536877647,
    536878225,
    536878482,
    536879174,
    536879808,
    536881347,
    536882120
  ],
  "themes": [
    {
      "id": 1,
      "created_at": 1322605337,
      "name": "Action",
      "slug": "action",
      "updated_at": 1323289216,
      "url": "https://www.igdb.com/themes/action",
      "checksum": "63242b90-6c5a-a452-ea8e-b3fa57c471cb"
    },
    {
      "id": 18,
      "created_at": 1322605338,
      "name": "Science fiction",
      "slug": "science-fiction",
      "updated_at": 1323289216,
      "url": "https://www.igdb.com/themes/science-fiction",
      "checksum": "fa5fd07e-6958-d075-7bd7-5ddcd1d7a851"
    },
    {
      "id": 27,
      "created_at": 1322605339,
      "name": "Comedy",
      "slug": "comedy",
      "updated_at": 1323289216,
      "url": "https://www.igdb.com/themes/comedy",
      "checksum": "1a1392df-91c8-09d9-1809-d511fb625f14"
    }
  ],
  "total_rating": 92.08297236268807,
  "total_rating_count": 3446,
  "updated_at": 1719827184,
  "url": "https://www.igdb.com/games/portal-2",
  "videos": [
    {
      "id": 432,
      "game": 72,
      "name": "Trailer",
      "video_id": "mC_u9ZwlIUc",
      "checksum": "ed3676b2-709a-abe7-6457-776fa15cf3ef"
    },
    {
      "id": 16451,
      "game": 72,
      "name": "Trailer",
      "video_id": "9r0rlRqpkOw",
      "checksum": "4a96a9e6-8f96-4f7f-c6d8-471835c100be"
    },
    {
      "id": 17844,
      "game": 72,
      "name": "Trailer",
      "video_id": "Qgl1otNanh0",
      "checksum": "bf08de84-b4de-eca5-85ac-3543736c9794"
    },
    {
      "id": 17845,
      "game": 72,
      "name": "Trailer",
      "video_id": "SQb-e7p0KmQ",
      "checksum": "e2ffd82f-7d44-35bb-2696-68a3488b718a"
    }
  ],
  "websites": [
    {
      "id": 17869,
      "category": 1,
      "game": 72,
      "trusted": false,
      "url": "http://www.thinkwithportals.com/",
      "checksum": "c2d5f8d1-6178-75f3-18ec-7b23c114d396"
    },
    {
      "id": 17870,
      "category": 13,
      "game": 72,
      "trusted": true,
      "url": "https://store.steampowered.com/app/620",
      "checksum": "d622151c-d8cf-8843-c3e7-65d50f29b460"
    },
    {
      "id": 41194,
      "category": 3,
      "game": 72,
      "trusted": true,
      "url": "https://en.wikipedia.org/wiki/Portal_2",
      "checksum": "b40db784-417c-2f63-4c5e-b45a8cdba054"
    },
    {
      "id": 41195,
      "category": 4,
      "game": 72,
      "trusted": true,
      "url": "https://www.facebook.com/Portal",
      "checksum": "936dbbda-3698-362b-7fbe-56e5234de2b3"
    },
    {
      "id": 150881,
      "category": 9,
      "game": 72,
      "trusted": true,
      "url": "https://www.youtube.com/user/Valve",
      "checksum": "f64c60a1-46f6-8e18-bb0f-114891e70261"
    },
    {
      "id": 150882,
      "category": 5,
      "game": 72,
      "trusted": true,
      "url": "https://twitter.com/valvesoftware",
      "checksum": "096a3b5a-008a-6042-8678-fbe6845ef85d"
    },
    {
      "id": 150883,
      "category": 2,
      "game": 72,
      "trusted": false,
      "url": "https://theportalwiki.com/wiki/Portal_2",
      "checksum": "02d302e6-ace7-a642-2a87-7c15cbbbc39c"
    },
    {
      "id": 332601,
      "category": 6,
      "game": 72,
      "trusted": true,
      "url": "https://www.twitch.tv/directory/game/Portal%202",
      "checksum": "5ad23ff6-fc6c-74ba-8d0d-0acb84f16815"
    }
  ],
  "checksum": "3a4f2d35-6b5b-3f75-b999-48af4502e105",
  "language_supports": [
    260224,
    260225,
    260226,
    260227,
    260228,
    260230,
    260231,
    260232,
    260233,
    260234,
    260235,
    260236,
    260237,
    260238,
    260239,
    260240,
    260241,
    260242,
    260243,
    260244,
    260245,
    260246,
    260247,
    260248,
    260249,
    260250
  ],
  "game_localizations": [
    726
  ],
  "collections": [
    87
  ]
}